{
	"configurations" : 
	[
		{
			"directories" : 
			[
				{
					"build" : ".",
					"jsonFile" : "directory-.-Debug-d0094a50bb2071803777.json",
					"minimumCMakeVersion" : 
					{
						"string" : "3.0.0"
					},
					"projectIndex" : 0,
					"source" : ".",
					"targetIndexes" : 
					[
						0,
						1,
						2,
						3,
						4,
						5,
						6
					]
				}
			],
			"name" : "Debug",
			"projects" : 
			[
				{
					"directoryIndexes" : 
					[
						0
					],
					"name" : "main",
					"targetIndexes" : 
					[
						0,
						1,
						2,
						3,
						4,
						5,
						6
					]
				}
			],
			"targets" : 
			[
				{
					"directoryIndex" : 0,
					"id" : "ALL_BUILD::@6890427a1f51a3e7e1df",
					"jsonFile" : "target-ALL_BUILD-Debug-26f43c8a8230e42424ad.json",
					"name" : "ALL_BUILD",
					"projectIndex" : 0
				},
				{
					"directoryIndex" : 0,
					"id" : "Continuous::@6890427a1f51a3e7e1df",
					"jsonFile" : "target-Continuous-Debug-721c1cef23ac2914a214.json",
					"name" : "Continuous",
					"projectIndex" : 0
				},
				{
					"directoryIndex" : 0,
					"id" : "Experimental::@6890427a1f51a3e7e1df",
					"jsonFile" : "target-Experimental-Debug-87d1b86ec92d4fe5b94f.json",
					"name" : "Experimental",
					"projectIndex" : 0
				},
				{
					"directoryIndex" : 0,
					"id" : "Nightly::@6890427a1f51a3e7e1df",
					"jsonFile" : "target-Nightly-Debug-349aee7d4b6b846ea54f.json",
					"name" : "Nightly",
					"projectIndex" : 0
				},
				{
					"directoryIndex" : 0,
					"id" : "NightlyMemoryCheck::@6890427a1f51a3e7e1df",
					"jsonFile" : "target-NightlyMemoryCheck-Debug-9f1370101cceb16401b0.json",
					"name" : "NightlyMemoryCheck",
					"projectIndex" : 0
				},
				{
					"directoryIndex" : 0,
					"id" : "ZERO_CHECK::@6890427a1f51a3e7e1df",
					"jsonFile" : "target-ZERO_CHECK-Debug-85b473eb7a4fdd3ccbdf.json",
					"name" : "ZERO_CHECK",
					"projectIndex" : 0
				},
				{
					"directoryIndex" : 0,
					"id" : "main::@6890427a1f51a3e7e1df",
					"jsonFile" : "target-main-Debug-f102e6b2ffe6a2de4620.json",
					"name" : "main",
					"projectIndex" : 0
				}
			]
		},
		{
			"directories" : 
			[
				{
					"build" : ".",
					"jsonFile" : "directory-.-Release-d0094a50bb2071803777.json",
					"minimumCMakeVersion" : 
					{
						"string" : "3.0.0"
					},
					"projectIndex" : 0,
					"source" : ".",
					"targetIndexes" : 
					[
						0,
						1,
						2,
						3,
						4,
						5,
						6
					]
				}
			],
			"name" : "Release",
			"projects" : 
			[
				{
					"directoryIndexes" : 
					[
						0
					],
					"name" : "main",
					"targetIndexes" : 
					[
						0,
						1,
						2,
						3,
						4,
						5,
						6
					]
				}
			],
			"targets" : 
			[
				{
					"directoryIndex" : 0,
					"id" : "ALL_BUILD::@6890427a1f51a3e7e1df",
					"jsonFile" : "target-ALL_BUILD-Release-26f43c8a8230e42424ad.json",
					"name" : "ALL_BUILD",
					"projectIndex" : 0
				},
				{
					"directoryIndex" : 0,
					"id" : "Continuous::@6890427a1f51a3e7e1df",
					"jsonFile" : "target-Continuous-Release-721c1cef23ac2914a214.json",
					"name" : "Continuous",
					"projectIndex" : 0
				},
				{
					"directoryIndex" : 0,
					"id" : "Experimental::@6890427a1f51a3e7e1df",
					"jsonFile" : "target-Experimental-Release-87d1b86ec92d4fe5b94f.json",
					"name" : "Experimental",
					"projectIndex" : 0
				},
				{
					"directoryIndex" : 0,
					"id" : "Nightly::@6890427a1f51a3e7e1df",
					"jsonFile" : "target-Nightly-Release-349aee7d4b6b846ea54f.json",
					"name" : "Nightly",
					"projectIndex" : 0
				},
				{
					"directoryIndex" : 0,
					"id" : "NightlyMemoryCheck::@6890427a1f51a3e7e1df",
					"jsonFile" : "target-NightlyMemoryCheck-Release-9f1370101cceb16401b0.json",
					"name" : "NightlyMemoryCheck",
					"projectIndex" : 0
				},
				{
					"directoryIndex" : 0,
					"id" : "ZERO_CHECK::@6890427a1f51a3e7e1df",
					"jsonFile" : "target-ZERO_CHECK-Release-85b473eb7a4fdd3ccbdf.json",
					"name" : "ZERO_CHECK",
					"projectIndex" : 0
				},
				{
					"directoryIndex" : 0,
					"id" : "main::@6890427a1f51a3e7e1df",
					"jsonFile" : "target-main-Release-2b7fb742bbbabb34b282.json",
					"name" : "main",
					"projectIndex" : 0
				}
			]
		},
		{
			"directories" : 
			[
				{
					"build" : ".",
					"jsonFile" : "directory-.-MinSizeRel-d0094a50bb2071803777.json",
					"minimumCMakeVersion" : 
					{
						"string" : "3.0.0"
					},
					"projectIndex" : 0,
					"source" : ".",
					"targetIndexes" : 
					[
						0,
						1,
						2,
						3,
						4,
						5,
						6
					]
				}
			],
			"name" : "MinSizeRel",
			"projects" : 
			[
				{
					"directoryIndexes" : 
					[
						0
					],
					"name" : "main",
					"targetIndexes" : 
					[
						0,
						1,
						2,
						3,
						4,
						5,
						6
					]
				}
			],
			"targets" : 
			[
				{
					"directoryIndex" : 0,
					"id" : "ALL_BUILD::@6890427a1f51a3e7e1df",
					"jsonFile" : "target-ALL_BUILD-MinSizeRel-26f43c8a8230e42424ad.json",
					"name" : "ALL_BUILD",
					"projectIndex" : 0
				},
				{
					"directoryIndex" : 0,
					"id" : "Continuous::@6890427a1f51a3e7e1df",
					"jsonFile" : "target-Continuous-MinSizeRel-721c1cef23ac2914a214.json",
					"name" : "Continuous",
					"projectIndex" : 0
				},
				{
					"directoryIndex" : 0,
					"id" : "Experimental::@6890427a1f51a3e7e1df",
					"jsonFile" : "target-Experimental-MinSizeRel-87d1b86ec92d4fe5b94f.json",
					"name" : "Experimental",
					"projectIndex" : 0
				},
				{
					"directoryIndex" : 0,
					"id" : "Nightly::@6890427a1f51a3e7e1df",
					"jsonFile" : "target-Nightly-MinSizeRel-349aee7d4b6b846ea54f.json",
					"name" : "Nightly",
					"projectIndex" : 0
				},
				{
					"directoryIndex" : 0,
					"id" : "NightlyMemoryCheck::@6890427a1f51a3e7e1df",
					"jsonFile" : "target-NightlyMemoryCheck-MinSizeRel-9f1370101cceb16401b0.json",
					"name" : "NightlyMemoryCheck",
					"projectIndex" : 0
				},
				{
					"directoryIndex" : 0,
					"id" : "ZERO_CHECK::@6890427a1f51a3e7e1df",
					"jsonFile" : "target-ZERO_CHECK-MinSizeRel-85b473eb7a4fdd3ccbdf.json",
					"name" : "ZERO_CHECK",
					"projectIndex" : 0
				},
				{
					"directoryIndex" : 0,
					"id" : "main::@6890427a1f51a3e7e1df",
					"jsonFile" : "target-main-MinSizeRel-dfb449b58423dc0c4a69.json",
					"name" : "main",
					"projectIndex" : 0
				}
			]
		},
		{
			"directories" : 
			[
				{
					"build" : ".",
					"jsonFile" : "directory-.-RelWithDebInfo-d0094a50bb2071803777.json",
					"minimumCMakeVersion" : 
					{
						"string" : "3.0.0"
					},
					"projectIndex" : 0,
					"source" : ".",
					"targetIndexes" : 
					[
						0,
						1,
						2,
						3,
						4,
						5,
						6
					]
				}
			],
			"name" : "RelWithDebInfo",
			"projects" : 
			[
				{
					"directoryIndexes" : 
					[
						0
					],
					"name" : "main",
					"targetIndexes" : 
					[
						0,
						1,
						2,
						3,
						4,
						5,
						6
					]
				}
			],
			"targets" : 
			[
				{
					"directoryIndex" : 0,
					"id" : "ALL_BUILD::@6890427a1f51a3e7e1df",
					"jsonFile" : "target-ALL_BUILD-RelWithDebInfo-26f43c8a8230e42424ad.json",
					"name" : "ALL_BUILD",
					"projectIndex" : 0
				},
				{
					"directoryIndex" : 0,
					"id" : "Continuous::@6890427a1f51a3e7e1df",
					"jsonFile" : "target-Continuous-RelWithDebInfo-721c1cef23ac2914a214.json",
					"name" : "Continuous",
					"projectIndex" : 0
				},
				{
					"directoryIndex" : 0,
					"id" : "Experimental::@6890427a1f51a3e7e1df",
					"jsonFile" : "target-Experimental-RelWithDebInfo-87d1b86ec92d4fe5b94f.json",
					"name" : "Experimental",
					"projectIndex" : 0
				},
				{
					"directoryIndex" : 0,
					"id" : "Nightly::@6890427a1f51a3e7e1df",
					"jsonFile" : "target-Nightly-RelWithDebInfo-349aee7d4b6b846ea54f.json",
					"name" : "Nightly",
					"projectIndex" : 0
				},
				{
					"directoryIndex" : 0,
					"id" : "NightlyMemoryCheck::@6890427a1f51a3e7e1df",
					"jsonFile" : "target-NightlyMemoryCheck-RelWithDebInfo-9f1370101cceb16401b0.json",
					"name" : "NightlyMemoryCheck",
					"projectIndex" : 0
				},
				{
					"directoryIndex" : 0,
					"id" : "ZERO_CHECK::@6890427a1f51a3e7e1df",
					"jsonFile" : "target-ZERO_CHECK-RelWithDebInfo-85b473eb7a4fdd3ccbdf.json",
					"name" : "ZERO_CHECK",
					"projectIndex" : 0
				},
				{
					"directoryIndex" : 0,
					"id" : "main::@6890427a1f51a3e7e1df",
					"jsonFile" : "target-main-RelWithDebInfo-059e770875afc56ff194.json",
					"name" : "main",
					"projectIndex" : 0
				}
			]
		}
	],
	"kind" : "codemodel",
	"paths" : 
	{
		"build" : "C:/Workspace/Programming/Cpp/Experimental/build",
		"source" : "C:/Workspace/Programming/Cpp/Experimental/src"
	},
	"version" : 
	{
		"major" : 2,
		"minor" : 4
	}
}
